{
  "name": "Hurricane II",
  "type": "Fighter",
  "nationality": "British",
  "service": "AIRFORCE",
  "designation": "RAF-",
  "altitude": "MEDIUM",
  "takeoff": "CARRIER",
  "landing": "LAND",
  "naval": {
    "modifier": 0,
    "full": 0,
    "half": 0
  },
  "land": {
    "modifier": 1,
    "full": 1,
    "half": 1
  },
  "air": {
    "modifier": 1,
    "full": 3,
    "half": 2
  },
  "performance": {
    "range": 6,
    "endurance": 1
  },
  "frame": {
    "frame": 1,
    "fragile": false
  }
}