{
  "name": "Spitfire V",
  "type": "Fighter",
  "nationality": "British",
  "service": "AIRFORCE",
  "designation": "RAF-",
  "altitude": "HIGH",
  "takeoff": "CARRIER",
  "landing": "LAND",
  "navalWarship": {
    "modifier": 0,
    "full": 0,
    "half": 0
  },
  "navalTransport": {
    "modifier": 0,
    "full": 0,
    "half": 0
  },
  "land": {
    "modifier": 0,
    "full": 0,
    "half": 0
  },
  "air": {
    "modifier": 1,
    "full": 4,
    "half": 2
  },
  "performance": {
    "range": 5,
    "endurance": 1
  },
  "frame": {
    "frame": 2,
    "fragile": false
  },
  "config": [
    "NONE",
    "DROP_TANKS",
    "SEARCH"
  ]
}